{
  "scripts": [
    {
      "output": "lib/jquery/dist/jquery.min.js",
      "input": [
        "node_modules/jquery/dist/jquery.min.js",
        "wwwroot/lib/jquery/dist/jquery-vertical-loop.js",
        "node_modules/jquery.cookie/jquery.cookie.js"
      ]
    },
    {
      "output": "lib/sweetalert2/dist/sweetalert2.min.js",
      "input": [
        "node_modules/sweetalert2/dist/sweetalert2.min.js"
      ]
    },
    {
      "output": "lib/swiper/swiper-bundle.min.js",
      "input": [
        "node_modules/swiper/swiper-bundle.min.js"
      ]
    },
    {
      "output": "lib/jquery-plugin-c-share/dist/jquery.c-share.min.js",
      "input": [
        "node_modules/jquery-plugin-c-share/dist/jquery.c-share.js"
      ]
    },
    {
      "output": "lib/jquery-twzipcode/jquery.twzipcode.min.js",
      "input": [
        "node_modules/jquery-twzipcode/jquery.twzipcode.min.js"
      ]
    },
    {
      "output": "lib/masonry-layout/dist/masonry.pkgd.min.js",
      "input": [
        "node_modules/masonry-layout/dist/masonry.pkgd.js"
      ]
    },
    {
      "output": "Shared/shared.min.js",
      "input": [
        "wwwroot/Shared/js/AnchorPoint.js",
        "wwwroot/Shared/js/DirectoryGetData.js",
        "wwwroot/Shared/js/Frame.js",
        "wwwroot/Shared/js/HoverEffect.js",
        "wwwroot/Shared/js/LinkWithIcon.js",
        "wwwroot/Shared/js/ShareBlock.js",
        "wwwroot/Shared/js/Sitemap.js",
        "wwwroot/Shared/js/Swiper.js",
        "wwwroot/Shared/js/ViewTypeChange.js",
        "wwwroot/Shared/js/Activity.js"
      ]
    }
  ],
  "styles": [
    {
      "output": "lib/sweetalert2/dist/sweetalert2.min.css",
      "input": [
        "node_modules/sweetalert2/dist/sweetalert2.css"
      ]
    },
    {
      "output": "lib/fortawesome/css/all.min.css",
      "input": [
        "node_modules/@fortawesome/fontawesome-free/css/all.css"
      ]
    },
    {
      "output": "lib/swiper/swiper-bundle.min.css",
      "input": [
        "node_modules/swiper/swiper-bundle.css"
      ]
    },
    {
      "output": "Shared/shared.min.css",
      "input": [
        "wwwroot/Shared/css/AnchorPoint.css",
        "wwwroot/Shared/css/Directory.css",
        "wwwroot/Shared/css/Frame.css",
        "wwwroot/Shared/css/HoverEffect.css",
        "wwwroot/Shared/css/Swiper.css",
        "wwwroot/Shared/css/Activity.less"
      ]
    }
  ],
  "scriptMappings": [
    {
      "outputFolder": "lib/swiper/",
      "input": [
        "node_modules/swiper/swiper-bundle.min.js.map"
      ]
    }
  ]
}
